nets_generators/__init__.py
nets_generators/dining_philosophers.py
nets_generators/dining_philosophers_with_dict.py
nets_generators/generate_slotted_ring.py
nets_generators/milners_cyclic_scheduler.py
nets_generators/mutual_exclusion.py
unfoldings/__init__.py
unfoldings/alg/__init__.py
unfoldings/alg/concurrency_relation.py
unfoldings/alg/possible_extensions.py
unfoldings/alg/priority_queue.py
unfoldings/cutoff_settings/__init__.py
unfoldings/cutoff_settings/abstract.py
unfoldings/cutoff_settings/idle.py
unfoldings/cutoff_settings/mark.py
unfoldings/decorations/__init__.py
unfoldings/decorations/abstract.py
unfoldings/decorations/colors.py
unfoldings/decorations/idle.py
unfoldings/decorations/labels.py
unfoldings/obj/__init__.py
unfoldings/obj/condition.py
unfoldings/obj/event.py
unfoldings/obj/prefix.py
unfoldings/order_settings/__init__.py
unfoldings/order_settings/abstract.py
unfoldings/order_settings/basic.py
unfoldings/order_settings/config_length_utils.py
unfoldings/order_settings/foata.py
unfoldings/order_settings/idle.py
unfoldings/unfolding_algorithms/__init__.py
unfoldings/unfolding_algorithms/standard.py
unfoldings/unfolding_algorithms/n_safe/__init__.py
unfoldings/unfolding_algorithms/n_safe/build_prefix.py
unfoldings/unfolding_algorithms/n_safe/condition.py
unfoldings/unfolding_algorithms/n_safe/event.py
unfoldings/unfolding_algorithms/n_safe/possible_extensions.py
pm4py_pn_unfoldings-1.0.2.dist-info/LICENSE
pm4py_pn_unfoldings-1.0.2.dist-info/METADATA
pm4py_pn_unfoldings-1.0.2.dist-info/WHEEL
pm4py_pn_unfoldings-1.0.2.dist-info/top_level.txt
pm4py_pn_unfoldings-1.0.2.dist-info/RECORD
